stickerbook_puzzle_solver/__init__.py
stickerbook_puzzle_solver/equation_lhs.py
stickerbook_puzzle_solver/stickerbook_puzzle.py
stickerbook_puzzle_solver-0.1.6.dist-info/LICENSE
stickerbook_puzzle_solver-0.1.6.dist-info/WHEEL
stickerbook_puzzle_solver-0.1.6.dist-info/METADATA
stickerbook_puzzle_solver-0.1.6.dist-info/RECORD
