Metadata-Version: 2.1
Name: stickerbook-puzzle-solver
Version: 0.1.6
Summary: Solving a family of puzzles seen on mathoffstickerbook.com
Home-page: https://github.com/SmokyFurby/stickerbook
License: MIT
Author: Belgin Seymenoglu
Author-email: belgin.seymenoglu.10@ucl.ac.uk
Requires-Python: >3.10
Classifier: License :: OSI Approved :: MIT License
Classifier: Programming Language :: Python :: 3
Classifier: Programming Language :: Python :: 3.11
Requires-Dist: click (>=8.1)
Requires-Dist: numpy (>=1.22)
Project-URL: Repository, https://github.com/SmokyFurby/stickerbook
